alibabacloud_umeng_apm20220214/__init__.py
alibabacloud_umeng_apm20220214/client.py
alibabacloud_umeng_apm20220214/models.py
alibabacloud_umeng_apm20220214-1.3.0.dist-info/LICENSE
alibabacloud_umeng_apm20220214-1.3.0.dist-info/METADATA
alibabacloud_umeng_apm20220214-1.3.0.dist-info/WHEEL
alibabacloud_umeng_apm20220214-1.3.0.dist-info/top_level.txt
alibabacloud_umeng_apm20220214-1.3.0.dist-info/RECORD
